engforge/__init__.py
engforge/_testing_components.py
engforge/analysis.py
engforge/attr_dynamics.py
engforge/attr_plotting.py
engforge/attr_signals.py
engforge/attr_slots.py
engforge/attr_solver.py
engforge/attributes.py
engforge/common.py
engforge/component_collections.py
engforge/components.py
engforge/configuration.py
engforge/dataframe.py
engforge/dynamics.py
engforge/engforge_attributes.py
engforge/env_var.py
engforge/locations.py
engforge/logging.py
engforge/patterns.py
engforge/problem_context.py
engforge/properties.py
engforge/reporting.py
engforge/solveable.py
engforge/solver.py
engforge/solver_utils.py
engforge/system.py
engforge/system_reference.py
engforge/tabulation.py
engforge/typing.py
engforge/datastores/__init__.py
engforge/datastores/data.py
engforge/datastores/gdocs.py
engforge/datastores/reporting.py
engforge/datastores/secrets.py
engforge/eng/__init__.py
engforge/eng/costs.py
engforge/eng/fluid_material.py
engforge/eng/geometry.py
engforge/eng/pipes.py
engforge/eng/prediction.py
engforge/eng/solid_materials.py
engforge/eng/structure.py
engforge/eng/structure_beams.py
engforge/eng/thermodynamics.py
engforge/test/__init__.py
engforge/test/_pre_test_structures.py
engforge/test/report_testing.py
engforge/test/test_airfilter.py
engforge/test/test_analysis.py
engforge/test/test_comp_iter.py
engforge/test/test_composition.py
engforge/test/test_costs.py
engforge/test/test_dynamics.py
engforge/test/test_dynamics_spaces.py
engforge/test/test_four_bar.py
engforge/test/test_modules.py
engforge/test/test_performance.py
engforge/test/test_pipes.py
engforge/test/test_problem.py
engforge/test/test_problem_deepscoping.py
engforge/test/test_slider_crank.py
engforge/test/test_solver.py
engforge/test/test_tabulation.py
engforge-0.3.0.dist-info/licenses/LICENSE
engforge-0.3.0.dist-info/METADATA
engforge-0.3.0.dist-info/WHEEL
engforge-0.3.0.dist-info/top_level.txt
engforge-0.3.0.dist-info/RECORD
