Metadata-Version: 2.4
Name: engforge
Version: 0.3.0
Summary: The Engineer's Framework
Author-email: Kevin Russell <olly@ottermatics.com>
License-Expression: MIT
Project-URL: Homepage, https://github.com/Ottermatics/engforge
Project-URL: Repository, https://github.com/Ottermatics/engforge
Project-URL: Documentation, https://ottermatics.github.io/engforge/
Classifier: Development Status :: 3 - Alpha
Classifier: Intended Audience :: Developers
Classifier: Programming Language :: Python :: 3
Classifier: Programming Language :: Python :: 3.9
Classifier: Programming Language :: Python :: 3.10
Classifier: Programming Language :: Python :: 3.11
Requires-Python: >=3.9
License-File: LICENSE
Requires-Dist: attrs~=23.2.0
Requires-Dist: arrow
Requires-Dist: deepdiff>=6.3.1
Requires-Dist: numpy==1.24.3
Requires-Dist: scipy
Requires-Dist: matplotlib~=3.8.1
Requires-Dist: jupyter
Requires-Dist: pandas
Requires-Dist: scikit-learn~=1.3.2
Requires-Dist: seaborn
Requires-Dist: tabulate
Requires-Dist: networkx-query==1.0.1
Requires-Dist: networkx>=2.5.1
Requires-Dist: black~=24.8.0
Requires-Dist: randomname~=0.2.1
Requires-Dist: termcolor
Requires-Dist: pyee
Requires-Dist: methodtools~=0.4.7
Requires-Dist: tomli>=1.2.0; python_version < "3.11"
Provides-Extra: dev
Requires-Dist: wheel; extra == "dev"
Requires-Dist: jinja2>=2.11.3; extra == "dev"
Requires-Dist: sphinx>=3.2.1; extra == "dev"
Requires-Dist: recommonmark>=0.6.0; extra == "dev"
Requires-Dist: sphinx-rtd-theme>=1.0.0; extra == "dev"
Provides-Extra: eng
Requires-Dist: control; extra == "eng"
Requires-Dist: fluids; extra == "eng"
Requires-Dist: CoolProp; extra == "eng"
Requires-Dist: sectionproperties~=3.1.2; extra == "eng"
Requires-Dist: PyniteFEA>=1.2.0; extra == "eng"
Provides-Extra: database
Requires-Dist: SQLAlchemy~=1.3.17; extra == "database"
Requires-Dist: SQLAlchemy-Utils; extra == "database"
Requires-Dist: psycopg2-binary; extra == "database"
Requires-Dist: diskcache>=5.6.1; extra == "database"
Requires-Dist: sqlalchemy-batch-inserts; extra == "database"
Provides-Extra: google
Requires-Dist: expiringdict~=1.2.2; extra == "google"
Requires-Dist: pygsheets==2.0.4; extra == "google"
Requires-Dist: pydrive2==1.8.1; extra == "google"
Provides-Extra: cloud
Requires-Dist: boto3; extra == "cloud"
Provides-Extra: distributed
Requires-Dist: ray[default]~=2.35.0; extra == "distributed"
Requires-Dist: ray[tune]~=2.35.0; extra == "distributed"
Provides-Extra: docs
Requires-Dist: sphinx>=7.0.0; extra == "docs"
Requires-Dist: sphinx-rtd-theme; extra == "docs"
Requires-Dist: pydata-sphinx-theme; extra == "docs"
Requires-Dist: sphinx-autodoc-typehints; extra == "docs"
Requires-Dist: myst-parser; extra == "docs"
Requires-Dist: sphinx_autodoc_typehints; extra == "docs"
Requires-Dist: toml~=0.10.2; extra == "docs"
Provides-Extra: all
Requires-Dist: engforge[cloud,database,dev,distributed,docs,eng,google]; extra == "all"
Dynamic: license-file
